{
  "id": 166816,
  "title": "Graded Assignments Dashboard Scores Incorrect/Missing",
  "slug": "graded-assignments-dashboard-scores-incorrect-missing",
  "post_stream": {
    "posts": [
      {
        "id": 593909,
        "post_number": 1,
        "username": "HARISH.S",
        "created_at": "2025-02-11T17:03:21.205Z",
        "like_count": 0,
        "cooked": "hello sir this is Harish. i completed and saved the week 2 and week 4 assignment. (didn\u2019t do week 3) but the graded assignment shows it is incomplete and the score is 0 for both the weeks . i am attaching the iages. kindly check and reply soon sir.\nimage1035\u00d7466 71 KB\nimage1035\u00d7453 27.2 KB\nthis is for week 4\nimage1678\u00d7847 141 KB\nimage1035\u00d7481 38.9 KB\nimage463\u00d7457 26.9 KB\nkindly check on this sir."
      },
      {
        "id": 593937,
        "post_number": 2,
        "username": "carlton",
        "created_at": "2025-02-11T18:21:52.000Z",
        "like_count": 0,
        "cooked": "Could you send me your email id. thanks."
      },
      {
        "id": 593944,
        "post_number": 3,
        "username": "24ds3000061",
        "created_at": "2025-02-11T18:46:15.785Z",
        "like_count": 0,
        "cooked": "Hi, the same issue persists for me for GA 2 and 4. I also did not attemp GA 3. Please look into this. My email id: 24ds3000061@ds.study.iitm.ac.in"
      },
      {
        "id": 593980,
        "post_number": 4,
        "username": "22f2001532",
        "created_at": "2025-02-12T03:23:21.693Z",
        "like_count": 0,
        "cooked": "My Graded assignment results are also not appearing in the dashboard. My email id is 22f2001532@ds.study.iitm.ac.in"
      },
      {
        "id": 593998,
        "post_number": 5,
        "username": "carlton",
        "created_at": "2025-02-12T05:18:27.095Z",
        "like_count": 0,
        "cooked": "@24ds3000061 @22f2001532\nCan you check the dashboard now, I\u2019ve been informed by operations that the scores have been pushed.\nGA 4 scores will be a little late to be pushed because there are some manual (i.e. automated using a custom written script) corrections that have to be made to Q4 for students who got Nur-Sultan as their city.\nKind regards"
      },
      {
        "id": 594002,
        "post_number": 6,
        "username": "22f2001532",
        "created_at": "2025-02-12T05:32:48.000Z",
        "like_count": 0,
        "cooked": "Thanks Carlton. Now the results are visible in the dashboard.\nThanks\nREVI"
      },
      {
        "id": 594072,
        "post_number": 7,
        "username": "22f2000559",
        "created_at": "2025-02-12T09:43:55.354Z",
        "like_count": 0,
        "cooked": "@carlton Sir in my case, in week 2 it is showing \u201cAbsent\u201d but I have attempted and saved the answers\nScreenshot 2025-02-12 151022427\u00d7596 28.1 KB\nScreenshot 2025-02-12 1511011035\u00d7434 21 KB\nMy email ID is 22f2000559@ds.study.iitm.ac.in.\nThank you."
      },
      {
        "id": 594080,
        "post_number": 8,
        "username": "carlton",
        "created_at": "2025-02-12T10:04:58.164Z",
        "like_count": 0,
        "cooked": "Hi @22f2000559\nI can confirm that our server did record your marks as 7, we will make a correction in the dashboard. Thanks for letting us know. My sincere apologies for the error.\nIf the marks on the dashboard are not changed within the next 7 days, please let us know. I will follow it up on my end and try to get the correction pushed as soon as possible.\nKind regards"
      },
      {
        "id": 594081,
        "post_number": 9,
        "username": "22f2000559",
        "created_at": "2025-02-12T10:06:10.638Z",
        "like_count": 0,
        "cooked": "Thank you so much Sir."
      },
      {
        "id": 594322,
        "post_number": 11,
        "username": "spartacus",
        "created_at": "2025-02-13T06:26:35.949Z",
        "like_count": 0,
        "cooked": "Screenshot 2025-02-13 105611251\u00d7317 14.2 KB\nanother embedding"
      },
      {
        "id": 594325,
        "post_number": 12,
        "username": "spartacus",
        "created_at": "2025-02-13T06:28:59.121Z",
        "like_count": 0,
        "cooked": "@carlton\nScreenshot 2025-02-13 1058351140\u00d7737 28.5 KB\nSir, In my dashboard i am getting Absent for GA3\nmy email id : 23f3001731@ds.study.iitm.ac.in\ni am not able to submit embeddings more than 1 so i am submitting it in another reply"
      },
      {
        "id": 594330,
        "post_number": 13,
        "username": "AnvithaV",
        "created_at": "2025-02-13T06:46:36.164Z",
        "like_count": 0,
        "cooked": "Sir, I have attempted the graded assignment 2 and also saved it but my score is showing as absent. Please look into the issue sir.\nMy email id is 23f1002071@ds.study.iitm.ac.in\ngraded assignment page1886\u00d7776 45.5 KB\ncourse dashboard (1)1919\u00d7828 156 KB\n@carlton @Jivraj"
      },
      {
        "id": 594515,
        "post_number": 14,
        "username": "dshail",
        "created_at": "2025-02-13T12:41:12.084Z",
        "like_count": 0,
        "cooked": "Same issue I\u2019m facing in my dashboard for week - 3 it shows I\u2019m absent although on portal it is showing my marks.\nPlease update my dashboard.\nE-mail: 22f2000905@ds.study.iitm.ac.in\nTDS 2025 Jan GA3\nTDS-W3-Results2472\u00d71636 313 KB"
      },
      {
        "id": 594516,
        "post_number": 15,
        "username": "dshail",
        "created_at": "2025-02-13T12:42:30.391Z",
        "like_count": 0,
        "cooked": "TDS 2025 Jan GA3-Dashboard2750\u00d71328 290 KB"
      },
      {
        "id": 595714,
        "post_number": 16,
        "username": "carlton",
        "created_at": "2025-02-16T02:59:23.470Z",
        "like_count": 0,
        "cooked": "Dear Students,\nOn the 13th of Feb (3 day ago at the time of this reply) an email was sent to all students with the subject [TDS Jan 2025] Grade Corrections. Please refer to that email.\nKind regards"
      },
      {
        "id": 595715,
        "post_number": 17,
        "username": "22f3000370",
        "created_at": "2025-02-15T04:32:36.973Z",
        "like_count": 0,
        "cooked": "Hello Sir/Mam,\nI had created this thread to inform that my marks for week -2 and week-4 graded assignment have not yet been updated and showing in the dashboard. But I have attended it, Please resolve the issue and do the needful actions.\nRegards,\nSengathirsoorian E T\n(22f3000370@ds.study.iitm.ac.in)\nWeek -4\nScreenshot_20250215-0958161080\u00d71852 263 KB\nI can\u2019t be able to enclose another screenshot of week-2 ( marks-5) as I was a new user."
      },
      {
        "id": 595713,
        "post_number": 19,
        "username": "carlton",
        "created_at": "2025-02-16T02:57:22.000Z",
        "like_count": 0,
        "cooked": "On the 13th of Feb (3 day ago at the time of this reply) an email was sent to all students with the subject [TDS Jan 2025] Grade Corrections. Please refer to that email.\nKind regards"
      },
      {
        "id": 595692,
        "post_number": 20,
        "username": "23F3004407_RATANPRIY",
        "created_at": "2025-02-15T20:50:32.496Z",
        "like_count": 0,
        "cooked": "Screenshot (674)1920\u00d71080 273 KB\n@Carlton D\u2019Silva sir can u please see this why it\u2019s given zero, it should be 8 right n in my dashboard it\u2019s showing absent so what i should do ?"
      },
      {
        "id": 595780,
        "post_number": 21,
        "username": "carlton",
        "created_at": "2025-02-16T06:31:56.151Z",
        "like_count": 0,
        "cooked": "Please refer to this post\n\n\n\n\nGRADED ASSIGNMENT RESULT NOT SHOWING , kindly check on this Tools in Data Science\n\n\n    On the 13th of Feb (3 day ago at the time of this reply) an email was sent to all students with the subject [TDS Jan 2025] Grade Corrections. Please refer to that email. \nKind regards\n  \n\n"
      },
      {
        "id": 595802,
        "post_number": 22,
        "username": "23F3004407_RATANPRIY",
        "created_at": "2025-02-16T07:08:03.000Z",
        "like_count": 0,
        "cooked": "Okk sir , n sir can u please tell me in which live session u have discussed regarding project becoz till week 3 i have see only n i having confusion in project so i want to see the session of project"
      }
    ]
  }
}
